BFHScheckers/__init__.py
BFHScheckers/board.py
BFHScheckers/board_initializer.py
BFHScheckers/board_searcher.py
BFHScheckers/game.py
BFHScheckers/piece.py
checkers/__init__.py
checkers/board.py
checkers/board_initializer.py
checkers/board_searcher.py
checkers/game.py
checkers/piece.py
test/__init__.py
test/test_game_over.py
test/test_possible_moves.py
test/test_winner.py
imparaai_BFHScheckers_for_BFHS_programming-1.4.2.4.dist-info/LICENSE
imparaai_BFHScheckers_for_BFHS_programming-1.4.2.4.dist-info/METADATA
imparaai_BFHScheckers_for_BFHS_programming-1.4.2.4.dist-info/WHEEL
imparaai_BFHScheckers_for_BFHS_programming-1.4.2.4.dist-info/top_level.txt
imparaai_BFHScheckers_for_BFHS_programming-1.4.2.4.dist-info/RECORD
